{
    "subjects": [
        {
            "rating": {
                "max": 10,
                "average": 8.9,
                "details": {
                    "1": 550.0,
                    "3": 27159.0,
                    "2": 2185.0,
                    "5": 153134.0,
                    "4": 98334.0
                },
                "stars": "45",
                "min": 0
            },
            "genres": [
                "\u52a8\u4f5c",
                "\u4f20\u8bb0",
                "\u5267\u60c5"
            ],
            "title": "\u52c7\u6562\u7684\u5fc3",
            "casts": [
                {
                    "avatars": {
                        "small": "http://img3.doubanio.com\/view\/celebrity\/s_ratio_celebrity\/public\/p1485855325.98.jpg",
                        "large": "http://img3.doubanio.com\/view\/celebrity\/s_ratio_celebrity\/public\/p1485855325.98.jpg",
                        "medium": "http://img3.doubanio.com\/view\/celebrity\/s_ratio_celebrity\/public\/p1485855325.98.jpg"
                    },
                    "name_en": "Mel Gibson",
                    "name": "\u6885\u5c14\u00b7\u5409\u5e03\u68ee",
                    "alt": "https:\/\/movie.douban.com\/celebrity\/1054530\/",
                    "id": "1054530"
                },
                {
                    "avatars": {
                        "small": "http://img3.doubanio.com\/view\/celebrity\/s_ratio_celebrity\/public\/p410.jpg",
                        "large": "http://img3.doubanio.com\/view\/celebrity\/s_ratio_celebrity\/public\/p410.jpg",
                        "medium": "http://img3.doubanio.com\/view\/celebrity\/s_ratio_celebrity\/public\/p410.jpg"
                    },
                    "name_en": "Sophie Marceau",
                    "name": "\u82cf\u83f2\u00b7\u739b\u7d22",
                    "alt": "https:\/\/movie.douban.com\/celebrity\/1040543\/",
                    "id": "1040543"
                },
                {
                    "avatars": {
                        "small": "http://img3.doubanio.com\/view\/celebrity\/s_ratio_celebrity\/public\/p1213.jpg",
                        "large": "http://img3.doubanio.com\/view\/celebrity\/s_ratio_celebrity\/public\/p1213.jpg",
                        "medium": "http://img3.doubanio.com\/view\/celebrity\/s_ratio_celebrity\/public\/p1213.jpg"
                    },
                    "name_en": "Brian Cox",
                    "name": "\u5e03\u83b1\u6069\u00b7\u8003\u514b\u65af",
                    "alt": "https:\/\/movie.douban.com\/celebrity\/1019027\/",
                    "id": "1019027"
                }
            ],
            "durations": [
                "177 \u5206\u949f"
            ],
            "collect_count": 528518,
            "mainland_pubdate": "",
            "has_video": true,
            "original_title": "Braveheart",
            "subtype": "movie",
            "directors": [
                {
                    "avatars": {
                        "small": "http://img3.doubanio.com\/view\/celebrity\/s_ratio_celebrity\/public\/p1485855325.98.jpg",
                        "large": "http://img3.doubanio.com\/view\/celebrity\/s_ratio_celebrity\/public\/p1485855325.98.jpg",
                        "medium": "http://img3.doubanio.com\/view\/celebrity\/s_ratio_celebrity\/public\/p1485855325.98.jpg"
                    },
                    "name_en": "Mel Gibson",
                    "name": "\u6885\u5c14\u00b7\u5409\u5e03\u68ee",
                    "alt": "https:\/\/movie.douban.com\/celebrity\/1054530\/",
                    "id": "1054530"
                }
            ],
            "pubdates": [
                "1995-05-18(\u897f\u96c5\u56fe\u7535\u5f71\u8282)",
                "1995-05-24(\u7f8e\u56fd)"
            ],
            "year": "1995",
            "images": {
                "small": "http://img3.doubanio.com\/view\/photo\/s_ratio_poster\/public\/p1374546770.jpg",
                "large": "http://img3.doubanio.com\/view\/photo\/s_ratio_poster\/public\/p1374546770.jpg",
                "medium": "http://img3.doubanio.com\/view\/photo\/s_ratio_poster\/public\/p1374546770.jpg"
            },
            "alt": "https:\/\/movie.douban.com\/subject\/1294639\/",
            "id": "1294639"
        },
        {
            "rating": {
                "max": 10,
                "average": 8.7,
                "details": {
                    "1": 967.0,
                    "3": 56598.0,
                    "2": 4106.0,
                    "5": 234889.0,
                    "4": 197087.0
                },
                "stars": "45",
                "min": 0
            },
            "genres": [
                "\u5267\u60c5",
                "\u5947\u5e7b",
                "\u7231\u60c5"
            ],
            "title": "\u526a\u5200\u624b\u7231\u5fb7\u534e",
            "casts": [
                {
                    "avatars": {
                        "small": "http://img3.doubanio.com\/view\/celebrity\/s_ratio_celebrity\/public\/p562.jpg",
                        "large": "http://img3.doubanio.com\/view\/celebrity\/s_ratio_celebrity\/public\/p562.jpg",
                        "medium": "http://img3.doubanio.com\/view\/celebrity\/s_ratio_celebrity\/public\/p562.jpg"
                    },
                    "name_en": "Johnny Depp",
                    "name": "\u7ea6\u7ff0\u5c3c\u00b7\u5fb7\u666e",
                    "alt": "https:\/\/movie.douban.com\/celebrity\/1054456\/",
                    "id": "1054456"
                },
                {
                    "avatars": {
                        "small": "http://img3.doubanio.com\/view\/celebrity\/s_ratio_celebrity\/public\/p31537.jpg",
                        "large": "http://img3.doubanio.com\/view\/celebrity\/s_ratio_celebrity\/public\/p31537.jpg",
                        "medium": "http://img3.doubanio.com\/view\/celebrity\/s_ratio_celebrity\/public\/p31537.jpg"
                    },
                    "name_en": "Winona Ryder",
                    "name": "\u8587\u8bfa\u5a1c\u00b7\u745e\u5fb7",
                    "alt": "https:\/\/movie.douban.com\/celebrity\/1012519\/",
                    "id": "1012519"
                },
                {
                    "avatars": {
                        "small": "http://img3.doubanio.com\/view\/celebrity\/s_ratio_celebrity\/public\/p4774.jpg",
                        "large": "http://img3.doubanio.com\/view\/celebrity\/s_ratio_celebrity\/public\/p4774.jpg",
                        "medium": "http://img3.doubanio.com\/view\/celebrity\/s_ratio_celebrity\/public\/p4774.jpg"
                    },
                    "name_en": "Dianne Wiest",
                    "name": "\u9edb\u5b89\u00b7\u97e6\u65af\u7279",
                    "alt": "https:\/\/movie.douban.com\/celebrity\/1002725\/",
                    "id": "1002725"
                }
            ],
            "durations": [
                "105\u5206\u949f"
            ],
            "collect_count": 899741,
            "mainland_pubdate": "",
            "has_video": true,
            "original_title": "Edward Scissorhands",
            "subtype": "movie",
            "directors": [
                {
                    "avatars": {
                        "small": "http://img3.doubanio.com\/view\/celebrity\/s_ratio_celebrity\/public\/p44690.jpg",
                        "large": "http://img3.doubanio.com\/view\/celebrity\/s_ratio_celebrity\/public\/p44690.jpg",
                        "medium": "http://img3.doubanio.com\/view\/celebrity\/s_ratio_celebrity\/public\/p44690.jpg"
                    },
                    "name_en": "Tim Burton",
                    "name": "\u8482\u59c6\u00b7\u6ce2\u987f",
                    "alt": "https:\/\/movie.douban.com\/celebrity\/1019002\/",
                    "id": "1019002"
                }
            ],
            "pubdates": [
                "1990-12-06(\u7f8e\u56fd)"
            ],
            "year": "1990",
            "images": {
                "small": "http://img3.doubanio.com\/view\/photo\/s_ratio_poster\/public\/p480956937.jpg",
                "large": "http://img3.doubanio.com\/view\/photo\/s_ratio_poster\/public\/p480956937.jpg",
                "medium": "http://img3.doubanio.com\/view\/photo\/s_ratio_poster\/public\/p480956937.jpg"
            },
            "alt": "https:\/\/movie.douban.com\/subject\/1292370\/",
            "id": "1292370"
        },
        {
            "rating": {
                "max": 10,
                "average": 8.7,
                "details": {
                    "1": 705.0,
                    "3": 40516.0,
                    "2": 2964.0,
                    "5": 199215.0,
                    "4": 161845.0
                },
                "stars": "45",
                "min": 0
            },
            "genres": [
                "\u5267\u60c5",
                "\u60ac\u7591",
                "\u79d1\u5e7b"
            ],
            "title": "\u8774\u8776\u6548\u5e94",
            "casts": [
                {
                    "avatars": {
                        "small": "http://img3.doubanio.com\/view\/celebrity\/s_ratio_celebrity\/public\/p49829.jpg",
                        "large": "http://img3.doubanio.com\/view\/celebrity\/s_ratio_celebrity\/public\/p49829.jpg",
                        "medium": "http://img3.doubanio.com\/view\/celebrity\/s_ratio_celebrity\/public\/p49829.jpg"
                    },
                    "name_en": "Ashton Kutcher",
                    "name": "\u963f\u4ec0\u987f\u00b7\u5e93\u5f7b",
                    "alt": "https:\/\/movie.douban.com\/celebrity\/1041016\/",
                    "id": "1041016"
                },
                {
                    "avatars": {
                        "small": "http://img3.doubanio.com\/view\/celebrity\/s_ratio_celebrity\/public\/p10772.jpg",
                        "large": "http://img3.doubanio.com\/view\/celebrity\/s_ratio_celebrity\/public\/p10772.jpg",
                        "medium": "http://img3.doubanio.com\/view\/celebrity\/s_ratio_celebrity\/public\/p10772.jpg"
                    },
                    "name_en": "Melora Walters",
                    "name": "\u6885\u6d1b\u62c9\u00b7\u6c83\u5c14\u7279\u65af",
                    "alt": "https:\/\/movie.douban.com\/celebrity\/1027275\/",
                    "id": "1027275"
                },
                {
                    "avatars": {
                        "small": "http://img3.doubanio.com\/view\/celebrity\/s_ratio_celebrity\/public\/p2552.jpg",
                        "large": "http://img3.doubanio.com\/view\/celebrity\/s_ratio_celebrity\/public\/p2552.jpg",
                        "medium": "http://img3.doubanio.com\/view\/celebrity\/s_ratio_celebrity\/public\/p2552.jpg"
                    },
                    "name_en": "Amy Smart",
                    "name": "\u827e\u7c73\u00b7\u65af\u9a6c\u7279",
                    "alt": "https:\/\/movie.douban.com\/celebrity\/1000048\/",
                    "id": "1000048"
                }
            ],
            "durations": [
                "113\u5206\u949f",
                "120\u5206\u949f(\u5bfc\u6f14\u526a\u8f91\u7248)"
            ],
            "collect_count": 760788,
            "mainland_pubdate": "",
            "has_video": true,
            "original_title": "The Butterfly Effect",
            "subtype": "movie",
            "directors": [
                {
                    "avatars": {
                        "small": "http://img3.doubanio.com\/view\/celebrity\/s_ratio_celebrity\/public\/p47492.jpg",
                        "large": "http://img3.doubanio.com\/view\/celebrity\/s_ratio_celebrity\/public\/p47492.jpg",
                        "medium": "http://img3.doubanio.com\/view\/celebrity\/s_ratio_celebrity\/public\/p47492.jpg"
                    },
                    "name_en": "Eric Bress",
                    "name": "\u57c3\u91cc\u514b\u00b7\u5e03\u96f7\u65af",
                    "alt": "https:\/\/movie.douban.com\/celebrity\/1279265\/",
                    "id": "1279265"
                },
                {
                    "avatars": {
                        "small": "http://img3.doubanio.com\/view\/celebrity\/s_ratio_celebrity\/public\/p1481012767.62.jpg",
                        "large": "http://img3.doubanio.com\/view\/celebrity\/s_ratio_celebrity\/public\/p1481012767.62.jpg",
                        "medium": "http://img3.doubanio.com\/view\/celebrity\/s_ratio_celebrity\/public\/p1481012767.62.jpg"
                    },
                    "name_en": "J. Mackye Gruber",
                    "name": "J\u00b7\u9ea6\u57fa\u00b7\u683c\u9c81\u4f2f",
                    "alt": "https:\/\/movie.douban.com\/celebrity\/1285555\/",
                    "id": "1285555"
                }
            ],
            "pubdates": [
                "2004-01-23(\u7f8e\u56fd)"
            ],
            "year": "2004",
            "images": {
                "small": "http://img3.doubanio.com\/view\/photo\/s_ratio_poster\/public\/p2209066019.jpg",
                "large": "http://img3.doubanio.com\/view\/photo\/s_ratio_poster\/public\/p2209066019.jpg",
                "medium": "http://img3.doubanio.com\/view\/photo\/s_ratio_poster\/public\/p2209066019.jpg"
            },
            "alt": "https:\/\/movie.douban.com\/subject\/1292343\/",
            "id": "1292343"
        },
        {
            "rating": {
                "max": 10,
                "average": 8.9,
                "details": {
                    "1": 194.0,
                    "3": 22480.0,
                    "2": 1064.0,
                    "5": 152907.0,
                    "4": 118592.0
                },
                "stars": "45",
                "min": 0
            },
            "genres": [
                "\u4f20\u8bb0",
                "\u72af\u7f6a",
                "\u5267\u60c5"
            ],
            "title": "\u732b\u9f20\u6e38\u620f",
            "casts": [
                {
                    "avatars": {
                        "small": "http://img3.doubanio.com\/view\/celebrity\/s_ratio_celebrity\/public\/p470.jpg",
                        "large": "http://img3.doubanio.com\/view\/celebrity\/s_ratio_celebrity\/public\/p470.jpg",
                        "medium": "http://img3.doubanio.com\/view\/celebrity\/s_ratio_celebrity\/public\/p470.jpg"
                    },
                    "name_en": "Leonardo DiCaprio",
                    "name": "\u83b1\u6602\u7eb3\u591a\u00b7\u8fea\u5361\u666e\u91cc\u5965",
                    "alt": "https:\/\/movie.douban.com\/celebrity\/1041029\/",
                    "id": "1041029"
                },
                {
                    "avatars": {
                        "small": "http://img3.doubanio.com\/view\/celebrity\/s_ratio_celebrity\/public\/p28603.jpg",
                        "large": "http://img3.doubanio.com\/view\/celebrity\/s_ratio_celebrity\/public\/p28603.jpg",
                        "medium": "http://img3.doubanio.com\/view\/celebrity\/s_ratio_celebrity\/public\/p28603.jpg"
                    },
                    "name_en": "Tom Hanks",
                    "name": "\u6c64\u59c6\u00b7\u6c49\u514b\u65af",
                    "alt": "https:\/\/movie.douban.com\/celebrity\/1054450\/",
                    "id": "1054450"
                },
                {
                    "avatars": {
                        "small": "http://img3.doubanio.com\/view\/celebrity\/s_ratio_celebrity\/public\/p1375077890.89.jpg",
                        "large": "http://img3.doubanio.com\/view\/celebrity\/s_ratio_celebrity\/public\/p1375077890.89.jpg",
                        "medium": "http://img3.doubanio.com\/view\/celebrity\/s_ratio_celebrity\/public\/p1375077890.89.jpg"
                    },
                    "name_en": "Christopher Walken",
                    "name": "\u514b\u91cc\u65af\u6258\u5f17\u00b7\u6c83\u80af",
                    "alt": "https:\/\/movie.douban.com\/celebrity\/1053574\/",
                    "id": "1053574"
                }
            ],
            "durations": [
                "141 \u5206\u949f"
            ],
            "collect_count": 475358,
            "mainland_pubdate": "",
            "has_video": true,
            "original_title": "Catch Me If You Can",
            "subtype": "movie",
            "directors": [
                {
                    "avatars": {
                        "small": "http://img3.doubanio.com\/view\/celebrity\/s_ratio_celebrity\/public\/p34602.jpg",
                        "large": "http://img3.doubanio.com\/view\/celebrity\/s_ratio_celebrity\/public\/p34602.jpg",
                        "medium": "http://img3.doubanio.com\/view\/celebrity\/s_ratio_celebrity\/public\/p34602.jpg"
                    },
                    "name_en": "Steven Spielberg",
                    "name": "\u53f2\u8482\u6587\u00b7\u65af\u76ae\u5c14\u4f2f\u683c",
                    "alt": "https:\/\/movie.douban.com\/celebrity\/1054440\/",
                    "id": "1054440"
                }
            ],
            "pubdates": [
                "2002-12-16(\u6d1b\u6749\u77f6\u9996\u6620)",
                "2002-12-25(\u7f8e\u56fd)"
            ],
            "year": "2002",
            "images": {
                "small": "http://img3.doubanio.com\/view\/photo\/s_ratio_poster\/public\/p453924541.jpg",
                "large": "http://img3.doubanio.com\/view\/photo\/s_ratio_poster\/public\/p453924541.jpg",
                "medium": "http://img3.doubanio.com\/view\/photo\/s_ratio_poster\/public\/p453924541.jpg"
            },
            "alt": "https:\/\/movie.douban.com\/subject\/1305487\/",
            "id": "1305487"
        },
        {
            "rating": {
                "max": 10,
                "average": 8.9,
                "details": {
                    "1": 582.0,
                    "3": 24150.0,
                    "2": 1711.0,
                    "5": 147987.0,
                    "4": 96480.0
                },
                "stars": "45",
                "min": 0
            },
            "genres": [
                "\u5267\u60c5",
                "\u7231\u60c5",
                "\u540c\u6027"
            ],
            "title": "\u6625\u5149\u4e4d\u6cc4",
            "casts": [
                {
                    "avatars": {
                        "small": "http://img3.doubanio.com\/view\/celebrity\/s_ratio_celebrity\/public\/p67.jpg",
                        "large": "http://img3.doubanio.com\/view\/celebrity\/s_ratio_celebrity\/public\/p67.jpg",
                        "medium": "http://img3.doubanio.com\/view\/celebrity\/s_ratio_celebrity\/public\/p67.jpg"
                    },
                    "name_en": "Leslie Cheung",
                    "name": "\u5f20\u56fd\u8363",
                    "alt": "https:\/\/movie.douban.com\/celebrity\/1003494\/",
                    "id": "1003494"
                },
                {
                    "avatars": {
                        "small": "http://img3.doubanio.com\/view\/celebrity\/s_ratio_celebrity\/public\/p33525.jpg",
                        "large": "http://img3.doubanio.com\/view\/celebrity\/s_ratio_celebrity\/public\/p33525.jpg",
                        "medium": "http://img3.doubanio.com\/view\/celebrity\/s_ratio_celebrity\/public\/p33525.jpg"
                    },
                    "name_en": "Tony Leung Chiu Wai",
                    "name": "\u6881\u671d\u4f1f",
                    "alt": "https:\/\/movie.douban.com\/celebrity\/1115918\/",
                    "id": "1115918"
                },
                {
                    "avatars": {
                        "small": "http://img3.doubanio.com\/view\/celebrity\/s_ratio_celebrity\/public\/p1453574419.48.jpg",
                        "large": "http://img3.doubanio.com\/view\/celebrity\/s_ratio_celebrity\/public\/p1453574419.48.jpg",
                        "medium": "http://img3.doubanio.com\/view\/celebrity\/s_ratio_celebrity\/public\/p1453574419.48.jpg"
                    },
                    "name_en": "Chen Chang",
                    "name": "\u5f20\u9707",
                    "alt": "https:\/\/movie.douban.com\/celebrity\/1077991\/",
                    "id": "1077991"
                }
            ],
            "durations": [
                "96\u5206\u949f"
            ],
            "collect_count": 450723,
            "mainland_pubdate": "",
            "has_video": false,
            "original_title": "\u6625\u5149\u4e4d\u6d29",
            "subtype": "movie",
            "directors": [
                {
                    "avatars": {
                        "small": "http://img3.doubanio.com\/view\/celebrity\/s_ratio_celebrity\/public\/p1418226223.7.jpg",
                        "large": "http://img3.doubanio.com\/view\/celebrity\/s_ratio_celebrity\/public\/p1418226223.7.jpg",
                        "medium": "http://img3.doubanio.com\/view\/celebrity\/s_ratio_celebrity\/public\/p1418226223.7.jpg"
                    },
                    "name_en": "Kar Wai Wong",
                    "name": "\u738b\u5bb6\u536b",
                    "alt": "https:\/\/movie.douban.com\/celebrity\/1041024\/",
                    "id": "1041024"
                }
            ],
            "pubdates": [
                "1997-05-17(\u621b\u7eb3\u7535\u5f71\u8282)",
                "1997-05-30(\u9999\u6e2f)"
            ],
            "year": "1997",
            "images": {
                "small": "http://img3.doubanio.com\/view\/photo\/s_ratio_poster\/public\/p465939041.jpg",
                "large": "http://img3.doubanio.com\/view\/photo\/s_ratio_poster\/public\/p465939041.jpg",
                "medium": "http://img3.doubanio.com\/view\/photo\/s_ratio_poster\/public\/p465939041.jpg"
            },
            "alt": "https:\/\/movie.douban.com\/subject\/1292679\/",
            "id": "1292679"
        },
        {
            "rating": {
                "max": 10,
                "average": 8.8,
                "details": {
                    "1": 370.0,
                    "3": 25786.0,
                    "2": 1616.0,
                    "5": 153611.0,
                    "4": 117815.0
                },
                "stars": "45",
                "min": 0
            },
            "genres": [
                "\u5267\u60c5"
            ],
            "title": "\u5fc3\u7075\u6355\u624b",
            "casts": [
                {
                    "avatars": {
                        "small": "http://img3.doubanio.com\/view\/celebrity\/s_ratio_celebrity\/public\/p620.jpg",
                        "large": "http://img3.doubanio.com\/view\/celebrity\/s_ratio_celebrity\/public\/p620.jpg",
                        "medium": "http://img3.doubanio.com\/view\/celebrity\/s_ratio_celebrity\/public\/p620.jpg"
                    },
                    "name_en": "Matt Damon",
                    "name": "\u9a6c\u7279\u00b7\u8fbe\u8499",
                    "alt": "https:\/\/movie.douban.com\/celebrity\/1054443\/",
                    "id": "1054443"
                },
                {
                    "avatars": {
                        "small": "http://img3.doubanio.com\/view\/celebrity\/s_ratio_celebrity\/public\/p103.jpg",
                        "large": "http://img3.doubanio.com\/view\/celebrity\/s_ratio_celebrity\/public\/p103.jpg",
                        "medium": "http://img3.doubanio.com\/view\/celebrity\/s_ratio_celebrity\/public\/p103.jpg"
                    },
                    "name_en": "Robin Williams",
                    "name": "\u7f57\u5bbe\u00b7\u5a01\u5ec9\u59c6\u65af",
                    "alt": "https:\/\/movie.douban.com\/celebrity\/1009241\/",
                    "id": "1009241"
                },
                {
                    "avatars": {
                        "small": "http://img3.doubanio.com\/view\/celebrity\/s_ratio_celebrity\/public\/p1552457947.91.jpg",
                        "large": "http://img3.doubanio.com\/view\/celebrity\/s_ratio_celebrity\/public\/p1552457947.91.jpg",
                        "medium": "http://img3.doubanio.com\/view\/celebrity\/s_ratio_celebrity\/public\/p1552457947.91.jpg"
                    },
                    "name_en": "Ben Affleck",
                    "name": "\u672c\u00b7\u963f\u5f17\u83b1\u514b",
                    "alt": "https:\/\/movie.douban.com\/celebrity\/1054417\/",
                    "id": "1054417"
                }
            ],
            "durations": [
                "126 \u5206\u949f"
            ],
            "collect_count": 492785,
            "mainland_pubdate": "",
            "has_video": true,
            "original_title": "Good Will Hunting",
            "subtype": "movie",
            "directors": [
                {
                    "avatars": {
                        "small": "http://img3.doubanio.com\/view\/celebrity\/s_ratio_celebrity\/public\/p461.jpg",
                        "large": "http://img3.doubanio.com\/view\/celebrity\/s_ratio_celebrity\/public\/p461.jpg",
                        "medium": "http://img3.doubanio.com\/view\/celebrity\/s_ratio_celebrity\/public\/p461.jpg"
                    },
                    "name_en": "Gus Van Sant",
                    "name": "\u683c\u65af\u00b7\u8303\u00b7\u6851\u7279",
                    "alt": "https:\/\/movie.douban.com\/celebrity\/1041021\/",
                    "id": "1041021"
                }
            ],
            "pubdates": [
                "1997-12-05(\u7f8e\u56fd)"
            ],
            "year": "1997",
            "images": {
                "small": "http://img3.doubanio.com\/view\/photo\/s_ratio_poster\/public\/p480965695.jpg",
                "large": "http://img3.doubanio.com\/view\/photo\/s_ratio_poster\/public\/p480965695.jpg",
                "medium": "http://img3.doubanio.com\/view\/photo\/s_ratio_poster\/public\/p480965695.jpg"
            },
            "alt": "https:\/\/movie.douban.com\/subject\/1292656\/",
            "id": "1292656"
        }
    ]
}